synclangs/__about__.py
synclangs/__init__.py
synclangs/__main__.py
synclangs/core.c
synclangs/core.cpython-310-darwin.so
synclangs/core.py
synclangs/dependencies.c
synclangs/dependencies.cpython-310-darwin.so
synclangs/dependencies.py
synclangs/validator.c
synclangs/validator.cpython-310-darwin.so
synclangs/validator.py
synclangs/cli/__init__.py
synclangs/cli/main.py
synclangs/codegen/__init__.c
synclangs/codegen/__init__.cpython-310-darwin.so
synclangs/codegen/__init__.py
synclangs/codegen/base.c
synclangs/codegen/base.cpython-310-darwin.so
synclangs/codegen/base.py
synclangs/codegen/cpp.c
synclangs/codegen/cpp.cpython-310-darwin.so
synclangs/codegen/cpp.py
synclangs/codegen/csharp.c
synclangs/codegen/csharp.cpython-310-darwin.so
synclangs/codegen/csharp.py
synclangs/codegen/go.c
synclangs/codegen/go.cpython-310-darwin.so
synclangs/codegen/go.py
synclangs/codegen/java.c
synclangs/codegen/java.cpython-310-darwin.so
synclangs/codegen/java.py
synclangs/codegen/python.c
synclangs/codegen/python.cpython-310-darwin.so
synclangs/codegen/python.py
synclangs/codegen/python_validators.c
synclangs/codegen/python_validators.cpython-310-darwin.so
synclangs/codegen/python_validators.py
synclangs/codegen/rust.c
synclangs/codegen/rust.cpython-310-darwin.so
synclangs/codegen/rust.py
synclangs/codegen/typescript.c
synclangs/codegen/typescript.cpython-310-darwin.so
synclangs/codegen/typescript.py
synclangs/codegen/typescript_validators.c
synclangs/codegen/typescript_validators.cpython-310-darwin.so
synclangs/codegen/typescript_validators.py
synclangs/config/__init__.c
synclangs/config/__init__.cpython-310-darwin.so
synclangs/config/__init__.py
synclangs/config/loader.c
synclangs/config/loader.cpython-310-darwin.so
synclangs/config/loader.py
synclangs/config/schema.c
synclangs/config/schema.cpython-310-darwin.so
synclangs/config/schema.py
synclangs/errors/__init__.c
synclangs/errors/__init__.cpython-310-darwin.so
synclangs/errors/__init__.py
synclangs/errors/codes.c
synclangs-0.2.0.dist-info/licenses/LICENSE
synclangs-0.2.0.dist-info/METADATA
synclangs-0.2.0.dist-info/WHEEL
synclangs-0.2.0.dist-info/entry_points.txt
synclangs-0.2.0.dist-info/top_level.txt
synclangs-0.2.0.dist-info/RECORD
