Metadata-Version: 2.4
Name: synclangs
Version: 0.2.0
Summary: Write types once, use everywhere
Author-email: Harjot Singh Rana <harjot@synclangs.com>
License-Expression: MIT
Project-URL: Homepage, https://synclangs.com
Project-URL: Documentation, https://docs.synclangs.com
Project-URL: Repository, https://github.com/HarjjotSinghh/synclangs
Keywords: types,codegen,typescript,python,schema
Classifier: Development Status :: 4 - Beta
Classifier: Programming Language :: Python :: 3.10
Classifier: Programming Language :: Python :: 3.11
Classifier: Programming Language :: Python :: 3.12
Classifier: Topic :: Software Development :: Code Generators
Classifier: Environment :: Console
Classifier: Intended Audience :: Developers
Requires-Python: >=3.10
License-File: LICENSE
Requires-Dist: typer>=0.9.0
Requires-Dist: rich>=13.0.0
Requires-Dist: lark>=1.1.0
Requires-Dist: pydantic>=2.0.0
Requires-Dist: watchdog>=3.0.0
Requires-Dist: setuptools>=68.0
Requires-Dist: wheel
Requires-Dist: Cython>=3.0.0
Provides-Extra: dev
Requires-Dist: pytest>=7.0.0; extra == "dev"
Requires-Dist: pytest-cov>=4.0.0; extra == "dev"
Requires-Dist: hypothesis>=6.0.0; extra == "dev"
Requires-Dist: ruff>=0.1.0; extra == "dev"
Requires-Dist: mypy>=1.0.0; extra == "dev"
Provides-Extra: docs
Requires-Dist: mkdocs>=1.5.0; extra == "docs"
Requires-Dist: mkdocs-material>=9.0.0; extra == "docs"
Requires-Dist: pymdown-extensions>=10.0.0; extra == "docs"
Dynamic: license-file
